sneaze_pynotify
resources
