Metadata-Version: 1.0
Name: sneazr-pynotify
Version: 0.1.1
Summary: Have nosetests notify to pynotify(fork of sneazr)
Home-page: http://github.com/teodor-pripoae/sneazr-pynotify
Author: Teodor Pripoae
Author-email: toni@netbaiji.com
License: UNKNOWN
Keywords: nose tests pynotify
Platform: UNKNOWN
